axesdnSDK/__init__.py
axesdnSDK/exception.py
axesdnSDK/ados/__init__.py
axesdnSDK/ados/ados_request.py
axesdnSDK/ados/client.py
axesdnSDK/ados/const.py
axesdnSDK/ados/exception.py
axesdnSDK/ados/connection/__init__.py
axesdnSDK/ados/connection/get_connection_range_monitor.py
axesdnSDK/ados/connection/get_connections.py
axesdnSDK/ados/connection/get_connections_instant_monitor.py
axesdnSDK/ados/router/__init__.py
axesdnSDK/ados/router/get_router_range_monitor.py
axesdnSDK/ados/router/get_router_sorted_topn.py
axesdnSDK/ados/router/get_routers.py
axesdnSDK/ados/router/get_routers_instant_monitor.py
axesdnSDK/example/__init__.py
axesdnSDK/example/get_instant_monitor.py
axesdnSDK/example/get_range_monitor.py
axesdnSDK/example/get_router_topn.py
axesdnSDK/example/get_routers_and_connections.py
axesdn_sdk-0.0.1.dist-info/LICENSE
axesdn_sdk-0.0.1.dist-info/METADATA
axesdn_sdk-0.0.1.dist-info/WHEEL
axesdn_sdk-0.0.1.dist-info/top_level.txt
axesdn_sdk-0.0.1.dist-info/RECORD
