Metadata-Version: 2.1
Name: axesdn-sdk
Version: 0.0.1
Summary: AXESDN SDK Library for Python
Author: AXESDN DEV Team
Author-email: devops@axesdn.com
License: Apache License 2.0
Platform: UNKNOWN
Classifier: Intended Audience :: Developers
Classifier: License :: OSI Approved :: Apache Software License
Classifier: Programming Language :: Python :: 3
Classifier: Topic :: Software Development
Requires-Python: >=3.7
License-File: LICENSE
Requires-Dist: requests (>=2.26.0)
